Workbook

Sheet Resumo
A1: RFI × Blueprint · Comparação por módulo
A2: Base oficial · 908 requisitos (793 NUCCI + 115 RH Benner). Números em azul vêm da RFI/Blueprint; os demais são fórmulas.
B4: RFI | E4: Blueprint | I4: Fora da aderência NUCCI
A5: Módulo | B5: Req. | C5: Entregue (Total + Parcial 70%) | D5: Aderência | E5: Entrega (Total + Parcial 70%) | F5: Parcial (50% e 30%) | G5: Não atende (RFI 0%) | H5: Benner (RH · fora NUCCI) | I5: Novos (fora da RFI) | J5: Itens com descrição
A6: Comercial | B6: 113 | C6: 111 | D6: =IFERROR(C6/B6,0) -> 0.98230088 | E6: 111 | F6: =COUNTIFS(Itens!$B$5:$B$112,$A6,Itens!$C$5:$C$112,"Parcial") -> 0 | G6: =COUNTIFS(Itens!$B$5:$B$112,$A6,Itens!$C$5:$C$112,"Não atende") -> 2 | H6: 0 | I6: =COUNTIFS(Itens!$B$5:$B$112,$A6,Itens!$C$5:$C$112,"Novo") -> 17 | J6: =COUNTIFS(Itens!$B$5:$B$112,$A6,Itens!$N$5:$N$112,"<>") -> 0
A7: Emissão | B7: 78 | C7: 78 | D7: =IFERROR(C7/B7,0) -> 1 | E7: 78 | F7: =COUNTIFS(Itens!$B$5:$B$112,$A7,Itens!$C$5:$C$112,"Parcial") -> 0 | G7: =COUNTIFS(Itens!$B$5:$B$112,$A7,Itens!$C$5:$C$112,"Não atende") -> 0 | H7: 0 | I7: =COUNTIFS(Itens!$B$5:$B$112,$A7,Itens!$C$5:$C$112,"Novo") -> 0 | J7: =COUNTIFS(Itens!$B$5:$B$112,$A7,Itens!$N$5:$N$112,"<>") -> 0
A8: Faturamento | B8: 74 | C8: 74 | D8: =IFERROR(C8/B8,0) -> 1 | E8: 74 | F8: =COUNTIFS(Itens!$B$5:$B$112,$A8,Itens!$C$5:$C$112,"Parcial") -> 0 | G8: =COUNTIFS(Itens!$B$5:$B$112,$A8,Itens!$C$5:$C$112,"Não atende") -> 0 | H8: 0 | I8: =COUNTIFS(Itens!$B$5:$B$112,$A8,Itens!$C$5:$C$112,"Novo") -> 0 | J8: =COUNTIFS(Itens!$B$5:$B$112,$A8,Itens!$N$5:$N$112,"<>") -> 0
A9: Financeiro | B9: 107 | C9: 99 | D9: =IFERROR(C9/B9,0) -> 0.92523364 | E9: 99 | F9: =COUNTIFS(Itens!$B$5:$B$112,$A9,Itens!$C$5:$C$112,"Parcial") -> 4 | G9: =COUNTIFS(Itens!$B$5:$B$112,$A9,Itens!$C$5:$C$112,"Não atende") -> 4 | H9: 0 | I9: =COUNTIFS(Itens!$B$5:$B$112,$A9,Itens!$C$5:$C$112,"Novo") -> 0 | J9: =COUNTIFS(Itens!$B$5:$B$112,$A9,Itens!$N$5:$N$112,"<>") -> 0
A10: Contabilidade | B10: 150 | C10: 110 | D10: =IFERROR(C10/B10,0) -> 0.73333333 | E10: 110 | F10: =COUNTIFS(Itens!$B$5:$B$112,$A10,Itens!$C$5:$C$112,"Parcial") -> 32 | G10: =COUNTIFS(Itens!$B$5:$B$112,$A10,Itens!$C$5:$C$112,"Não atende") -> 8 | H10: 0 | I10: =COUNTIFS(Itens!$B$5:$B$112,$A10,Itens!$C$5:$C$112,"Novo") -> 0 | J10: =COUNTIFS(Itens!$B$5:$B$112,$A10,Itens!$N$5:$N$112,"<>") -> 0
A11: Compras | B11: 99 | C11: 73 | D11: =IFERROR(C11/B11,0) -> 0.73737374 | E11: 73 | F11: =COUNTIFS(Itens!$B$5:$B$112,$A11,Itens!$C$5:$C$112,"Parcial") -> 11 | G11: =COUNTIFS(Itens!$B$5:$B$112,$A11,Itens!$C$5:$C$112,"Não atende") -> 15 | H11: 0 | I11: =COUNTIFS(Itens!$B$5:$B$112,$A11,Itens!$C$5:$C$112,"Novo") -> 0 | J11: =COUNTIFS(Itens!$B$5:$B$112,$A11,Itens!$N$5:$N$112,"<>") -> 1
A12: Estoque | B12: 33 | C12: 31 | D12: =IFERROR(C12/B12,0) -> 0.93939394 | E12: 31 | F12: =COUNTIFS(Itens!$B$5:$B$112,$A12,Itens!$C$5:$C$112,"Parcial") -> 1 | G12: =COUNTIFS(Itens!$B$5:$B$112,$A12,Itens!$C$5:$C$112,"Não atende") -> 1 | H12: 0 | I12: =COUNTIFS(Itens!$B$5:$B$112,$A12,Itens!$C$5:$C$112,"Novo") -> 0 | J12: =COUNTIFS(Itens!$B$5:$B$112,$A12,Itens!$N$5:$N$112,"<>") -> 0
A13: Corporativo | B13: 78 | C13: 73 | D13: =IFERROR(C13/B13,0) -> 0.93589744 | E13: 73 | F13: =COUNTIFS(Itens!$B$5:$B$112,$A13,Itens!$C$5:$C$112,"Parcial") -> 5 | G13: =COUNTIFS(Itens!$B$5:$B$112,$A13,Itens!$C$5:$C$112,"Não atende") -> 0 | H13: 0 | I13: =COUNTIFS(Itens!$B$5:$B$112,$A13,Itens!$C$5:$C$112,"Novo") -> 0 | J13: =COUNTIFS(Itens!$B$5:$B$112,$A13,Itens!$N$5:$N$112,"<>") -> 0
A14: Frota | B14: 26 | C14: 24 | D14: =IFERROR(C14/B14,0) -> 0.92307692 | E14: 24 | F14: =COUNTIFS(Itens!$B$5:$B$112,$A14,Itens!$C$5:$C$112,"Parcial") -> 2 | G14: =COUNTIFS(Itens!$B$5:$B$112,$A14,Itens!$C$5:$C$112,"Não atende") -> 0 | H14: 0 | I14: =COUNTIFS(Itens!$B$5:$B$112,$A14,Itens!$C$5:$C$112,"Novo") -> 4 | J14: =COUNTIFS(Itens!$B$5:$B$112,$A14,Itens!$N$5:$N$112,"<>") -> 0
A15: Oficina | B15: 35 | C15: 35 | D15: =IFERROR(C15/B15,0) -> 1 | E15: 35 | F15: =COUNTIFS(Itens!$B$5:$B$112,$A15,Itens!$C$5:$C$112,"Parcial") -> 0 | G15: =COUNTIFS(Itens!$B$5:$B$112,$A15,Itens!$C$5:$C$112,"Não atende") -> 0 | H15: 0 | I15: =COUNTIFS(Itens!$B$5:$B$112,$A15,Itens!$C$5:$C$112,"Novo") -> 0 | J15: =COUNTIFS(Itens!$B$5:$B$112,$A15,Itens!$N$5:$N$112,"<>") -> 0
A16: Total NUCCI | B16: =SUM(B6:B15) -> 793 | C16: =SUM(C6:C15) -> 708 | D16: =IFERROR(C16/B16,0) -> 0.89281211 | E16: =SUM(E6:E15) -> 708 | F16: =SUM(F6:F15) -> 55 | G16: =SUM(G6:G15) -> 30 | H16: 0 | I16: =COUNTIFS(Itens!$C$5:$C$112,"Novo") -> 23 | J16: =SUM(J6:J15) -> 1
A17: Recursos Humanos (Benner) | B17: 115 | C17: – | D17: – | E17: – | F17: – | G17: – | H17: 115 | I17: – | J17: –
A18: Total RFI (NUCCI + Benner) | B18: =B16+B17 -> 908 | C18: =C16 -> 708 | D18: – | E18: =E16 -> 708 | F18: =F16 -> 55 | G18: =G16 -> 30 | H18: =H16+H17 -> 115 | I18: =I16 -> 23 | J18: =J16 -> 1
A20: Fechamento | B20: =E18&" + "&F18&" + "&G18&" + "&H18&" = "&(E18+F18+G18+H18) -> 708 + 55 + 30 + 115 = 908 | G20: =IF(E18+F18+G18+H18=B18,"100% fechado","Verificar") -> 100% fechado
A21: Novos: 2 itens de WMS entram na contagem, mas o WMS não faz parte desta primeira fase.
A23: Andamento das descrições
A24: Status | B24: Itens | C24: % do total
A25: Pendente | B25: =COUNTIF(Itens!$Q$5:$Q$112,A25) -> 108 | C25: =IFERROR(B25/COUNTA(Itens!$A$5:$A$112),0) -> 1
A26: Em análise | B26: =COUNTIF(Itens!$Q$5:$Q$112,A26) -> 0 | C26: =IFERROR(B26/COUNTA(Itens!$A$5:$A$112),0) -> 0
A27: Validado | B27: =COUNTIF(Itens!$Q$5:$Q$112,A27) -> 0 | C27: =IFERROR(B27/COUNTA(Itens!$A$5:$A$112),0) -> 0
A28: Descartado | B28: =COUNTIF(Itens!$Q$5:$Q$112,A28) -> 0 | C28: =IFERROR(B28/COUNTA(Itens!$A$5:$A$112),0) -> 0
A29: Total de itens | B29: =COUNTA(Itens!$A$5:$A$112) -> 108 | C29: =SUM(C25:C28) -> 1

Sheet Itens
A1: Abertura dos itens · RFI × Blueprint
A2: Implantação NUCCI ERP · MADRI · Governança Instituto Államo — preencha as colunas amarelas (Descrição da equipe, Responsável, Data, Status).
A4: Item | B4: Módulo | C4: Categoria | D4: Agrupamento | E4: Processo / Seção | F4: Requisito / Descrição do gap | G4: Aderência | H4: Sem seção no Blueprint | I4: Forma de atendimento | J4: Criticidade | K4: WMS | L4: Solução proposta (Blueprint 5.1) | M4: Observação | N4: Descrição da equipe | O4: Responsável | P4: Data | Q4: Status
A5: L189 | B5: Compras | C5: Parcial | D5: Módulo de Compras (Suprimentos) | E5: 4.4.12.12 Processo Solicitação de Compras | F5: Programar o recebimento de Materiais | G5: Parcial 30% | H5: Não | I5: Customizável | K5: Não | N5: texto | P5: 46310 | Q5: Pendente
A6: L193 | B6: Compras | C6: Parcial | D6: Módulo de Compras (Suprimentos) | E6: 4.4.12.12 Processo Solicitação de Compras | F6: Permitir bloqueios automáticos de reposição de Produtos ou Grupos de Produtos sem disponibilidade Orçamentária / Financeira / Aprovação por alçada | G6: Parcial 30% | H6: Não | I6: Customizável | K6: Não | Q6: Pendente
A7: L212 | B7: Compras | C7: Parcial | D7: Módulo de Compras (Suprimentos) | E7: 4.4.12.12 Processo Solicitação de Compras (tema previsto; requisito não detalhado) | F7: Manter um "FollowUp" das OCS Ordens de Compra junto aos Fornecedores, com a possibilidade de consulta dos Emails enviados e sem resposta do Fornecedor | G7: Parcial 30% | H7: Não | I7: Customizável | K7: Não | Q7: Pendente
A8: L217 | B8: Compras | C8: Parcial | D8: Módulo de Compras (Suprimentos) | E8: 4.4.12.15 Processo Pedido de Compra | F8: Manter Tabela de Preços por Fornecedor e Produto | G8: Parcial 50% | H8: Não | I8: Customizável | K8: Não | Q8: Pendente
A9: L218 | B9: Compras | C9: Parcial | D9: Módulo de Compras (Suprimentos) | E9: 4.4.12.12 Processo Solicitação de Compras (tema previsto; requisito não detalhado) | F9: Permitir fórmulas de reajuste de Preços contratados (Valores, Percentuais, ...) | G9: Parcial 50% | H9: Não | I9: Customizável | K9: Não | Q9: Pendente
A10: L232 | B10: Compras | C10: Parcial | D10: Módulo de Compras (Suprimentos) | E10: 4.4.12.13 Processo Orçamento | F10: Controlar Contratos vinculados e subcontratações | G10: Parcial 50% | H10: Não | I10: Customizável | K10: Não | Q10: Pendente
A11: L234 | B11: Compras | C11: Parcial | D11: Módulo de Compras (Suprimentos) | E11: 4.4.12.13 Processo Orçamento | F11: Permitir alterações nos Contratos | G11: Parcial 50% | H11: Não | I11: Customizável | K11: Não | Q11: Pendente
A12: L268 | B12: Compras | C12: Parcial | D12: Módulo de Compras (Suprimentos) | E12: 4.4.12.16 Processo Pedido de Compras: Confirmação; 4.4.12.4 Cadastro Fornecedor/Grupo de Produtos/Serviço | F12: Gerar Demonstrativos por Comprador e com informações sobre “Lead Time” (para a área requisitante), Qualidade do Produto recebido, Preço e divergências na documentação na Avaliação do Comprador | G12: Parcial 50% | H12: Não | I12: Customizável | K12: Não | Q12: Pendente
A13: L269 | B13: Compras | C13: Parcial | D13: Módulo de Compras (Suprimentos) | E13: 4.4.12.4 Cadastro Fornecedor/Grupo de Produtos/Serviço; 4.4.12.7 Cadastro Produtos/Serviços | F13: Manter registro do responsável e o(s) motivo(s) da desativação de Grupos de Produtos, Produtos ou Materiais | G13: Parcial 30% | H13: Não | I13: Customizável | K13: Não | Q13: Pendente
A14: L280 | B14: Compras | C14: Parcial | D14: Módulo de Compras (Suprimentos) | E14: 4.4.12.12 Processo Solicitação de Compras | F14: Disponibilizar Relatórios de Controle de Metas (Compras x Receitas) considerando a Quantidade de Compras, agrupando por Tipos de Compra (Geral, Material de Consumo, Produtos, Serviços, ...) | G14: Parcial 50% | H14: Não | I14: Customizável | K14: Não | Q14: Pendente
A15: L287 | B15: Compras | C15: Parcial | D15: Módulo de Compras (Suprimentos) | E15: 4.4.12.12 Processo Solicitação de Compras | F15: Permitir e controlar projeções de compras baseadas no orçamento | G15: Parcial 50% | H15: Não | I15: Customizável | K15: Não | Q15: Pendente
A16: L317 | B16: Contabilidade | C16: Parcial | D16: Contabilidade | E16: 4.4.6.17 DRE (tema previsto; requisito não detalhado) | F16: Permitir criar visões gerencias por perfil de acesso [usuário] | G16: Parcial 50% | H16: Não | I16: Software de terceiro | K16: Não | Q16: Pendente
A17: L318 | B17: Contabilidade | C17: Parcial | D17: Contabilidade | E17: 4.4.6.17 DRE | F17: Permitir visão Drill Down da conta [leitura sub-nível] | G17: Parcial 50% | H17: Não | I17: Software de terceiro | K17: Não | Q17: Pendente
... A89: L1105 | B89: Estoque | C89: Não atende | D89: Controle de Estoque | E89: Sem seção no Blueprint | F89: Cadastrar produtos alternativos/substitutos e regras de equivalência | G89: Não Atende | H89: Sim | I89: Customizável | K89: Não | Q89: Pendente
A90: COM01 | B90: Comercial | C90: Novo | D90: Comercial/CRM | E90: 5.1 Lista de gaps | F90: Desconto sobre fatura tem que descontar % do vendedor. | G90: Novo | H90: Não | I90: Parametrização | J90: Média | K90: Não | L90: Configurar a comissão sobre o valor líquido da fatura (abatendo o desconto concedido) e validar com a planilha PCOM06. Se o padrão não atender, tratar via controle de mudanças. | M90: Decisão: A validar · Esforço: 8 h | Q90: Pendente
A91: COM02 | B91: Comercial | C91: Novo | D91: Comercial/CRM | E91: 5.1 Lista de gaps | F91: Desenvolvimento/ajuste de análise e validação de margem mínima. | G91: Novo | H91: Não | I91: Customização | J91: Média | K91: Não | L91: Desenvolver a validação de margem mínima na cotação e na tabela, com bloqueio ou alçada de aprovação abaixo da margem (regra a definir pelo Nilton). | M91: Decisão: A validar · Esforço: 8 h | Q91: Pendente
A92: COM03 | B92: Comercial | C92: Novo | D92: Comercial/CRM | E92: 5.1 Lista de gaps | F92: Bloquear emissão por % de NF quando o destinatário for DEDICADO (ex.: LIDER, FORMOSA, DrogaRaia). | G92: Novo | H92: Não | I92: Parametrização | J92: Média | K92: Não | L92: Parametrizar os destinatários dedicados (LIDER, FORMOSA, DrogaRaia) para bloquear o cálculo por % de NF e exigir tabela específica. | M92: Decisão: A validar · Esforço: 8 h | Q92: Pendente
A93: TMS01 | B93: Comercial | C93: Novo | D93: TMS | E93: 5.1 Lista de gaps | F93: Procedimento Operacional de Coleta para Controlar melhor a operação JADLOG | G93: Novo | H93: Não | I93: Processo | J93: Média | K93: Não | L93: Elaborar o procedimento operacional de coleta JADLOG (ordem de coleta, coleta, conferência e baixa) com a operação, alinhado ao processo de Coleta do TMS. | M93: Decisão: A validar · Esforço: 8 h | Q93: Pendente
A94: TMS02 | B94: Comercial | C94: Novo | D94: TMS | E94: 5.1 Lista de gaps | F94: VERIFICAR Impressão de etiqueta código de barras na operação e leitura de Etiqueta dos clientes | G94: Novo | H94: Não | I94: Parametrização | J94: Média | K94: Não | L94: Parametrizar o modelo de etiqueta e a impressora térmica e configurar a leitura das etiquetas dos clientes; testar na homologação. | M94: Decisão: A validar · Esforço: 8 h | Q94: Pendente
A95: TMS03 | B95: Comercial | C95: Novo | D95: TMS | E95: 5.1 Lista de gaps | F95: Separação Municipal entre Minuta/CTE | G95: Novo | H95: Não | I95: Parametrização | J95: Média | K95: Não | L95: Parametrizar a regra de emissão: origem e destino no mesmo município em Minuta/NFS-e e intermunicipal em CT-e; testar em homologação SEFAZ. | M95: Decisão: A validar · Esforço: 1 h | Q95: Pendente
A96: TMS04 | B96: Comercial | C96: Novo | D96: TMS | E96: 5.1 Lista de gaps | F96: Apólice de Seguros → responsabilidade dos parceiros aderirem ao PGR. | G96: Novo | H96: Não | I96: Processo | J96: Média | K96: Não | L96: A MADRI formaliza a adesão dos parceiros ao PGR/apólice; o Nucci parametriza a exigência de documentos e o bloqueio de embarque sem cobertura. | M96: Decisão: A validar · Esforço: 1 h | Q96: Pendente
A97: TMS05 | B97: Comercial | C97: Novo | D97: TMS | E97: 5.1 Lista de gaps | F97: Retenção de impostos de terceiros com o departamento FISCAL. | G97: Novo | H97: Não | I97: Parametrização | J97: Média | K97: Não | L97: Definir com o Fiscal e a contabilidade (Domínio) as regras de retenção sobre terceiros e parametrizar nas tabelas do Fiscal; revisar após a reforma tributária. | M97: Decisão: A validar · Esforço: 1 h | Q97: Pendente
A98: TMS06 | B98: Comercial | C98: Novo | D98: TMS | E98: 5.1 Lista de gaps | F98: KARTINEY enviará as regras da PGR. | G98: Novo | H98: Não | I98: Parametrização | J98: Média | K98: Não | L98: Receber as regras de PGR do Kartiney e parametrizar bloqueios e liberações no TMS e na gerenciadora de risco; testar na homologação. | M98: Decisão: A validar (regras PGR) · Esforço: 1 h | Q98: Pendente
A99: TMS07 | B99: Comercial | C99: Novo | D99: TMS | E99: 5.1 Lista de gaps | F99: RODOBENS cancela a SM da MADRID quando a JADLOG emite SM/MDFe com o mesmo veículo/motorista. | G99: Novo | H99: Não | I99: Processo | J99: Alta | K99: Não | L99: Reunião MADRI–JADLOG–RODOBENS para definir a regra de emissão de SM/MDF-e para o mesmo veículo e motorista; documentar o procedimento e incluir cenário de teste. | M99: Decisão: A validar · Esforço: 8 h | Q99: Pendente
A100: TMS08 | B100: Comercial | C100: Novo | D100: TMS | E100: 5.1 Lista de gaps | F100: Substituição do Envoy: baixa de entrega no MobiTruck com evidências obrigatórias (foto e localização) e ocorrências padronizadas. | G100: Novo | H100: Não | I100: Parametrização | J100: Alta | K100: Não | L100: Configurar o MobiTruck com foto e localização obrigatórias na baixa e ocorrências padronizadas; plano de descontinuação do Envoy e operação assistida (PWMS04). | M100: Decisão: A validar (PWMS04) · Esforço: 8 h | Q100: Pendente
A101: TMS09 | B101: Comercial | C101: Novo | D101: TMS | E101: 5.1 Lista de gaps | F101: Esteira com leitura do volume e indicação visual da rota em monitor, com contador volume corrente/total (01/40). | G101: Novo | H101: Não | I101: Customização | J101: Média | K101: Não | L101: Integrar a esteira, o leitor e o monitor para indicar a rota e o contador de volumes; especificação e orçamento em PWMS03. | M101: Decisão: A validar · Esforço: 1 h | Q101: Pendente
... A112: WMS02 | B112: WMS | C112: Novo | D112: WMS | E112: 5.1 Lista de gaps | F112: Controle de carga-valor (acima de ~R$ 500,00) com endereço de segurança e alerta de capacidade da área. | G112: Novo | H112: Não | I112: Parametrização | J112: Alta | K112: Sim | L112: Endereço de segurança obrigatório para volumes acima de ~R$ 500,00 e alerta de capacidade da área; revisar o layout (PWMS06). | M112: Decisão: Condicionado ao WMS · Esforço: 1 h | Q112: Pendente

Sheet Legenda
A1: Como usar esta planilha
A3: Células amarelas | B3: Campos para a equipe preencher na aba Itens: Descrição da equipe, Responsável, Data e Status.
A4: Números em azul | B4: Valores fixos vindos da RFI e do Blueprint (aba Resumo). O resto é calculado por fórmula.
A5: Status | B5: Escolha na lista: Pendente, Em análise, Validado ou Descartado. O Resumo conta automaticamente.
A6: Filtros | B6: A aba Itens é uma tabela: use as setas do cabeçalho para filtrar por módulo, categoria, status etc.
A7: Parcial | B7: Atendido só em parte (50% ou 30%). Não conta como entrega.
A8: Não atende | B8: A NUCCI marcou como Não Atende (0%). "Sem seção no Blueprint = Sim" indica pendência da seção 16: validar com a MADRI se é obrigatório ou desejável.
A9: Novo | B9: Necessidade que não estava na RFI (entrevistas e visita a Belém). Não entra na aderência. Os 2 itens de WMS ficam fora desta primeira fase.
A10: Benner | B10: Os 115 requisitos de RH ficam com a Benner, contratada à parte. Entram no total da RFI, mas não na aderência da NUCCI.
A11: Exemplo de preenchimento | B11: Descrição da equipe: "Validado com Compras em reunião; seguir com customização no sprint 3." · Responsável: Maria Souza · Data: 20/10/2026 · Status: Em análise
